nextprod.py
nextprod-1.0.dist-info/METADATA
nextprod-1.0.dist-info/WHEEL
nextprod-1.0.dist-info/top_level.txt
nextprod-1.0.dist-info/zip-safe
nextprod-1.0.dist-info/RECORD
