Metadata-Version: 2.1
Name: nextprod
Version: 1.0
Summary: Port of Julia's nextprod
Home-page: https://github.com/fasiha/nextprod-py
Author: Ahmed Fasih
Author-email: ahmed@aldebrn.me
License: Unlicense
Platform: UNKNOWN
